ubuntu_ppa_package_version_report/__init__.py
ubuntu_ppa_package_version_report/cli.py
ubuntu_ppa_package_version_report/launchpadagent.py
ubuntu_ppa_package_version_report/ubuntu_ppa_package_version_report.py
ubuntu_ppa_package_version_report-0.0.5.dist-info/AUTHORS.rst
ubuntu_ppa_package_version_report-0.0.5.dist-info/LICENSE
ubuntu_ppa_package_version_report-0.0.5.dist-info/METADATA
ubuntu_ppa_package_version_report-0.0.5.dist-info/WHEEL
ubuntu_ppa_package_version_report-0.0.5.dist-info/entry_points.txt
ubuntu_ppa_package_version_report-0.0.5.dist-info/top_level.txt
ubuntu_ppa_package_version_report-0.0.5.dist-info/RECORD
