Metadata-Version: 2.1
Name: ubuntu-ppa-package-version-report
Version: 0.0.5
Summary: Utility to Generate a report on the versions of packages in specified PPAs
Home-page: https://github.com/canonical/ubuntu_ppa_package_version_report
Author: Philip Roche
Author-email: phil.roche@canonical.com
License: GNU General Public License v3
Keywords: ubuntu_ppa_package_version_report
Platform: UNKNOWN
Classifier: Development Status :: 2 - Pre-Alpha
Classifier: Intended Audience :: Developers
Classifier: License :: OSI Approved :: GNU General Public License v3 (GPLv3)
Classifier: Natural Language :: English
Classifier: Programming Language :: Python :: 3
Classifier: Programming Language :: Python :: 3.6
Classifier: Programming Language :: Python :: 3.7
Classifier: Programming Language :: Python :: 3.8
Requires-Python: >=3.6
License-File: LICENSE
License-File: AUTHORS.rst
Requires-Dist: Click (>=7.0)
Requires-Dist: launchpadlib
